twilio_async/__init__.py
twilio_async/client.py
twilio_async/models/__init__.py
twilio_async/models/message.py
twilio_async/py.typed
twilio_python_async-0.2.3.dist-info/LICENSE
twilio_python_async-0.2.3.dist-info/METADATA
twilio_python_async-0.2.3.dist-info/WHEEL
twilio_python_async-0.2.3.dist-info/RECORD
