Metadata-Version: 2.1
Name: twilio-python-async
Version: 0.2.3
Summary: An asynchronous Twilio client
Home-page: https://github.com/sanders41/twilio-python-async
License: MIT
Keywords: twilio,async,python,sms,messaging
Author: Paul Sanders
Author-email: psanders1@gmail.com
Requires-Python: >=3.8,<4.0
Classifier: Development Status :: 7 - Inactive
Classifier: Intended Audience :: Developers
Classifier: License :: OSI Approved :: MIT License
Classifier: Operating System :: OS Independent
Classifier: Programming Language :: Python :: 3
Classifier: Programming Language :: Python :: 3.8
Classifier: Programming Language :: Python :: 3.9
Classifier: Programming Language :: Python :: 3.10
Classifier: Programming Language :: Python :: 3.11
Classifier: Typing :: Typed
Requires-Dist: httpx (>=0.23.3)
Requires-Dist: pydantic (>=1.10.4)
Project-URL: Documentation, https://github.com/sanders41/twilio-python-async
Project-URL: Repository, https://github.com/sanders41/twilio-python-async
